{
  "app": "executor",
  "version": "0.0.1",
  "category": "scalars.arithmetic",
  "name": "Absolute value: |x|",
  "id": "e935bbb5-c7f3-4c56-ada5-46b67aa641aa",
  "language": "java",
  "java": {
    "class": "net.algart.executors.modules.core.scalars.arithmetic.AbsNumber"
  },
  "in_ports": [
    {
      "value_type": "scalar",
      "name": "input"
    }
  ],
  "out_ports": [
    {
      "value_type": "scalar",
      "name": "output"
    },
    {
      "value_type": "scalar",
      "name": "negative",
      "hint": "\"true\" string if the source number was negative, \"false\" if not"
    }
  ],
  "controls": [
  ]
}